mangakatana/__init__.py
mangakatana/chapterlist.py
mangakatana/mangasearch.py
mangakatana/siterequests.py
mangakatana-0.3.1.dist-info/LICENSE
mangakatana-0.3.1.dist-info/METADATA
mangakatana-0.3.1.dist-info/WHEEL
mangakatana-0.3.1.dist-info/top_level.txt
mangakatana-0.3.1.dist-info/RECORD
