Metadata-Version: 2.1
Name: mangakatana
Version: 0.3.1
Summary: Query the mangatkatana.com site using BeautifulSoup
Home-page: https://github.com/nixonjoshua98/mangakatana
Author: Joshua Nixon
Author-email: joshuanixonofficial@gmail.com
License: MIT
Download-URL: https://github.com/nixonjoshua98/mangakatana/archive/0.3.1.tar.gz
Keywords: manga,manganelo,scrapper,web,mangakakalot,comic,manhwa,mangakatana
Platform: UNKNOWN
Classifier: Programming Language :: Python :: 3
Classifier: License :: OSI Approved :: MIT License
Classifier: Operating System :: OS Independent
Classifier: Development Status :: 5 - Production/Stable
Classifier: Intended Audience :: Developers
Classifier: Topic :: Software Development :: Build Tools
Requires-Python: >=3.7
License-File: LICENSE
Requires-Dist: bs4
Requires-Dist: requests
